Metadata-Version: 2.1
Name: immortal-client
Version: 0.0.3
Summary: Wonderful Immortals client
Home-page: https://github.com/goldenhand76/immortal-client
Author: goldenhand76
Author-email: goldenhand76 <rezazarindast76@gmail.com>
Maintainer-email: goldenhand76 <rezazarindast76@gmail.com>
License: MIT License
Project-URL: Homepage, https://github.com/goldenhand76/immortal_client
Project-URL: Documentation, https://github.com/goldenhand76/immortal_client
Project-URL: Repository, https://github.com/goldenhand76/immortal_client.git
Project-URL: Issues, https://github.com/goldenhand76/immortal_client/issues
Keywords: IoT,python,gRPC,kafka
Requires-Python: >=3.6
License-File: LICENSE
Requires-Dist: requests==2.31.0
